require_id/__init__.py
require_id/__version__.py
require_id/py.typed
require_id-0.0.0.dist-info/LICENSE
require_id-0.0.0.dist-info/WHEEL
require_id-0.0.0.dist-info/METADATA
require_id-0.0.0.dist-info/RECORD
